kpireport_slack/__init__.py
kpireport_slack/output.py
kpireport_slack-0.0.3.dist-info/METADATA
kpireport_slack-0.0.3.dist-info/WHEEL
kpireport_slack-0.0.3.dist-info/entry_points.txt
kpireport_slack-0.0.3.dist-info/top_level.txt
kpireport_slack-0.0.3.dist-info/RECORD
