Metadata-Version: 2.1
Name: kpireport-slack
Version: 0.0.3
Summary: UNKNOWN
Home-page: https://kpireporter.com
Author: KPI Reporter LLC
Author-email: dev@kpireporter.com
License: Prosperity Public License
Platform: UNKNOWN
Requires-Dist: kpireport
Requires-Dist: slackclient
